ci/environment-with-xesmf.yml
ci/environment.yml
roms_tools/__init__.py
roms_tools/constants.py
roms_tools/fill.py
roms_tools/plot.py
roms_tools/regrid.py
roms_tools/utils.py
roms_tools/vertical_coordinate.py
roms_tools/analysis/cdr_analysis.py
roms_tools/analysis/cdr_ensemble.py
roms_tools/analysis/roms_output.py
roms_tools/data/grids/GLORYS_global_grid.nc
roms_tools/datasets/download.py
roms_tools/datasets/lat_lon_datasets.py
roms_tools/datasets/river_datasets.py
roms_tools/datasets/roms_dataset.py
roms_tools/datasets/utils.py
roms_tools/setup/__init__.py
roms_tools/setup/boundary_forcing.py
roms_tools/setup/cdr_forcing.py
roms_tools/setup/cdr_release.py
roms_tools/setup/grid.py
roms_tools/setup/initial_conditions.py
roms_tools/setup/mask.py
roms_tools/setup/nesting.py
roms_tools/setup/river_forcing.py
roms_tools/setup/surface_forcing.py
roms_tools/setup/tides.py
roms_tools/setup/topography.py
roms_tools/setup/utils.py
roms_tools/tests/__init__.py
roms_tools/tests/test_fill.py
roms_tools/tests/test_regrid.py
roms_tools/tests/test_utils.py
roms_tools/tests/test_vertical_coordinate.py
roms_tools/tests/test_analysis/test_cdr_analysis.py
roms_tools/tests/test_analysis/test_cdr_ensemble.py
roms_tools/tests/test_analysis/test_roms_output.py
roms_tools/tests/test_datasets/test_lat_lon_datasets.py
roms_tools/tests/test_datasets/test_river_datasets.py
roms_tools/tests/test_datasets/test_roms_dataset.py
roms_tools/tests/test_datasets/test_utils.py
roms_tools/tests/test_setup/__init__.py
roms_tools/tests/test_setup/test_boundary_forcing.py
roms_tools/tests/test_setup/test_cdr_forcing.py
roms_tools/tests/test_setup/test_cdr_release.py
roms_tools/tests/test_setup/test_grid.py
roms_tools/tests/test_setup/test_initial_conditions.py
roms_tools/tests/test_setup/test_nesting.py
roms_tools/tests/test_setup/test_river_forcing.py
roms_tools/tests/test_setup/test_surface_forcing.py
roms_tools/tests/test_setup/test_tides.py
roms_tools/tests/test_setup/test_utils.py
roms_tools-3.4.0.dist-info/licenses/LICENSE
roms_tools-3.4.0.dist-info/METADATA
roms_tools-3.4.0.dist-info/WHEEL
roms_tools-3.4.0.dist-info/top_level.txt
roms_tools-3.4.0.dist-info/RECORD
