Metadata-Version: 2.4
Name: roms-tools
Version: 3.4.0
Summary: Tools for running and analysing UCLA-ROMS simulations
Author-email: Nora Loose <nora.loose@gmail.com>, Thomas Nicholas <tom@cworthy.org>, Scott Eilerman <scott.eilerman@cworthy.org>
License: Apache-2
Project-URL: Home, https://github.com/CWorthy-ocean/roms-tools
Project-URL: Documentation, https://roms-tools.readthedocs.io/en/latest/
Classifier: Development Status :: 3 - Alpha
Classifier: Intended Audience :: Science/Research
Classifier: Topic :: Scientific/Engineering
Classifier: License :: OSI Approved :: Apache Software License
Classifier: Operating System :: OS Independent
Classifier: Programming Language :: Python
Classifier: Programming Language :: Python :: 3.11
Classifier: Programming Language :: Python :: 3.12
Classifier: Programming Language :: Python :: 3.13
Requires-Python: >=3.11
License-File: LICENSE
Requires-Dist: xarray<2025.8.0,>=2022.6.0
Requires-Dist: numpy<2.3,>2.0
Requires-Dist: pooch
Requires-Dist: matplotlib
Requires-Dist: cartopy
Requires-Dist: packaging
Requires-Dist: scipy
Requires-Dist: gcm_filters>=0.5.1
Requires-Dist: netcdf4
Requires-Dist: PyYAML
Requires-Dist: pyamg
Requires-Dist: bottleneck
Requires-Dist: regionmask
Requires-Dist: xgcm>=0.9.0
Requires-Dist: numba>=0.61.2
Requires-Dist: pydantic<3,>2
Provides-Extra: dask
Requires-Dist: dask[diagnostics]; extra == "dask"
Requires-Dist: zarr; extra == "dask"
Provides-Extra: stream
Requires-Dist: dask[diagnostics]; extra == "stream"
Requires-Dist: gcsfs; extra == "stream"
Requires-Dist: zarr; extra == "stream"
Requires-Dist: copernicusmarine; extra == "stream"
Provides-Extra: notebooks
Requires-Dist: dask[diagnostics]; extra == "notebooks"
Requires-Dist: gcsfs; extra == "notebooks"
Requires-Dist: zarr; extra == "notebooks"
Requires-Dist: copernicusmarine; extra == "notebooks"
Requires-Dist: gdown; extra == "notebooks"
Requires-Dist: ipykernel; extra == "notebooks"
Requires-Dist: jupyter; extra == "notebooks"
Dynamic: license-file
